discordlists/__init__.py
discordlists/baseclient.py
discordlists/client.py
discordlists/exceptions.py
discordlists.py-1.1.1.dist-info/METADATA
discordlists.py-1.1.1.dist-info/RECORD
discordlists.py-1.1.1.dist-info/WHEEL
discordlists.py-1.1.1.dist-info/top_level.txt
