Metadata-Version: 2.1
Name: discordlists.py
Version: 1.1.1
Summary: A simple API wrapper for botblock.org providing server count posting to all bot lists and fetching botinformation from all.
Home-page: https://github.com/MattIPv4/discordlists.py/
Author: MattIPv4
License: UNKNOWN
Project-URL: Funding, http://patreon.mattcowley.co.uk/
Project-URL: Support, http://discord.mattcowley.co.uk/
Project-URL: Source, https://github.com/MattIPv4/discordlists.py/
Keywords: api wrapper discord bot bots stats statistics botblock server guild count list lists get post botlist
Platform: UNKNOWN
Classifier: License :: OSI Approved :: MIT License
Classifier: Programming Language :: Python :: 3
Classifier: Natural Language :: English
Classifier: Intended Audience :: Developers
Classifier: Operating System :: OS Independent
Requires-Python: >= 3.5
Requires-Dist: aiohttp
